ragents_frontend/__init__.py
ragents_frontend/__main__.py
ragents_frontend/py.typed
ragents_frontend/server.py
ragents_frontend/frontend_build/.next/app-build-manifest.json
ragents_frontend/frontend_build/.next/build-manifest.json
ragents_frontend/frontend_build/.next/package.json
ragents_frontend/frontend_build/.next/react-loadable-manifest.json
ragents_frontend/frontend_build/.next/trace
ragents_frontend/frontend_build/.next/cache/eslint/.cache_1wxwhe7
ragents_frontend/frontend_build/.next/cache/webpack/client-development/0.pack.gz
ragents_frontend/frontend_build/.next/cache/webpack/client-development/1.pack.gz
ragents_frontend/frontend_build/.next/cache/webpack/client-development/2.pack.gz
ragents_frontend/frontend_build/.next/cache/webpack/client-development/3.pack.gz
ragents_frontend/frontend_build/.next/cache/webpack/client-development/4.pack.gz
ragents_frontend/frontend_build/.next/cache/webpack/client-development/5.pack.gz
ragents_frontend/frontend_build/.next/cache/webpack/client-development/6.pack.gz
ragents_frontend/frontend_build/.next/cache/webpack/client-development/7.pack.gz
ragents_frontend/frontend_build/.next/cache/webpack/client-development/8.pack.gz
ragents_frontend/frontend_build/.next/cache/webpack/client-development/9.pack.gz
ragents_frontend/frontend_build/.next/cache/webpack/client-development/index.pack.gz
ragents_frontend/frontend_build/.next/cache/webpack/client-development/index.pack.gz.old
ragents_frontend/frontend_build/.next/cache/webpack/server-development/0.pack.gz
ragents_frontend/frontend_build/.next/cache/webpack/server-development/1.pack.gz
ragents_frontend/frontend_build/.next/cache/webpack/server-development/2.pack.gz
ragents_frontend/frontend_build/.next/cache/webpack/server-development/3.pack.gz
ragents_frontend/frontend_build/.next/cache/webpack/server-development/4.pack.gz
ragents_frontend/frontend_build/.next/cache/webpack/server-development/5.pack.gz
ragents_frontend-0.1.0.dist-info/METADATA
ragents_frontend-0.1.0.dist-info/WHEEL
ragents_frontend-0.1.0.dist-info/RECORD
