Metadata-Version: 2.4
Name: ragents-frontend
Version: 0.1.0
Summary: RAGents Frontend - A Python-embeddable Next.js frontend for RAG agents
Author-email: Mehran Moazeni <mehran1414@gmail.com>
Classifier: Development Status :: 3 - Alpha
Classifier: Intended Audience :: Developers
Classifier: Programming Language :: Python :: 3
Classifier: Programming Language :: Python :: 3.9
Classifier: Programming Language :: Python :: 3.10
Classifier: Programming Language :: Python :: 3.11
Classifier: Programming Language :: Python :: 3.12
Requires-Python: >=3.9
Requires-Dist: fastapi>=0.104.0
Requires-Dist: uvicorn>=0.24.0
Provides-Extra: dev
Requires-Dist: black>=23.0.0; extra == 'dev'
Requires-Dist: pytest>=7.4.0; extra == 'dev'
Requires-Dist: ruff>=0.1.0; extra == 'dev'
